<?xml version="1.0" encoding="gb2312"?>
<UIScene xmlns:xsi="http://www.w3.org/2001/XMLSchema-instance" xmlns:xsd="http://www.w3.org/2001/XMLSchema">
	<Resolution type="skip" width="2208" height="1242" />
	<Layer code="Img_floor" type="image" res="img_TYTC_0001" s9="1"  index="0" visible="true" opacity="255" width="840" height="877" posx="-8" posy="-8.5" bounds1="676" bounds2="191" bounds3="1516" bounds4="1068" />
	<Layer code="Btn_close" type="btn" res="img_TY_0004"  index="1" visible="true" opacity="255" width="108" height="103" posx="381" posy="400.5" bounds1="1431" bounds2="169" bounds3="1539" bounds4="272" />
	<Layer type="skip"/>
	<Layer code="Attribute" type="rect" parent="Attribute"  index="3" visible="true" opacity="255" width="0" height="0" posx="-1104" posy="621" bounds1="0" bounds2="0" bounds3="0" bounds4="0" >
		<Layer code="Img_informationframe_1" type="image" res="img_TY_0053"  index="0" visible="true" opacity="128" width="743" height="226" posx="-15.5" posy="-241" bounds1="717" bounds2="749" bounds3="1460" bounds4="975" />
		<Layer code="Text_life" fonttext="27"  index="1" type="text" content="生   命
" colorr="208.000945150852" colorg="181.284593939781" colorb="129.692999124527" font="FZY3JW--GB1-0" fontsize="18.1570148468018" visible="true" opacity="255" width="79" height="27" posx="-85.5" posy="-175.5" bounds1="979" bounds2="783" bounds3="1058" bounds4="810" />
		<Layer code="Text_lifevalue_number" fonttext="27"  index="2" type="text" content="+10000" colorr="255" colorg="249.996884465218" colorb="219.99614149332" font="FZY3JW--GB1-0" fontsize="27" visible="true" opacity="255" width="88" height="20" posx="49" posy="-175" bounds1="1109" bounds2="786" bounds3="1197" bounds4="806" />
		<Layer code="Img_basemap_2" type="image" res="img_DJBB_0012"  index="3" visible="true" opacity="255" width="282" height="46" posx="-246" posy="-84" bounds1="717" bounds2="682" bounds3="999" bounds4="728" />
		<Layer code="Text_attributepromotion" fonttext="30"  index="4" type="text" content="属性提升" colorr="255" colorg="227.996520996094" colorb="171.001281738281" font="FZY3JW--GB1-0" fontsize="20.1744594573975" visible="true" opacity="255" width="125" height="29" posx="-245.5" posy="-83.5" bounds1="796" bounds2="690" bounds3="921" bounds4="719" />
	</Layer>
	<Layer type="skip"/>
	<Layer code="Unlock" type="rect" parent="Unlock"  index="5" visible="true" opacity="255" width="0" height="0" posx="-1104" posy="621" bounds1="0" bounds2="0" bounds3="0" bounds4="0" >
		<Layer code="Img_informationframe_1" type="image" res="img_TY_0053"  index="0" visible="true" opacity="128" width="743" height="226" posx="-15.5" posy="88" bounds1="717" bounds2="420" bounds3="1460" bounds4="646" />
		<Layer code="Img_skill frame" type="image" res="img_TY_0052"  index="1" visible="true" opacity="255" width="174" height="174" posx="-261" posy="84" bounds1="756" bounds2="450" bounds3="930" bounds4="624" />
		<Layer code="Img_activemap" type="image" res="img_TY_0040"  index="2" visible="true" opacity="255" width="96" height="36" posx="-223" posy="17" bounds1="833" bounds2="586" bounds3="929" bounds4="622" />
		<Layer code="Img_active" type="image" res="img_TY_0065"  index="3" visible="true" opacity="255" width="58" height="32" posx="-214" posy="16" bounds1="861" bounds2="589" bounds3="919" bounds4="621" />
		<Layer code="Text_loong" fonttext="47"  index="4" type="text" content="龙飞凤舞啊" colorr="255" colorg="239.330248832703" colorb="107.000555992126" font="FZY3JW--GB1-0" fontsize="17.8465824127197" visible="true" opacity="255" width="243" height="46" posx="-26.5" posy="148" bounds1="956" bounds2="450" bounds3="1199" bounds4="496" />
		<Layer code="Text_heroquality" fonttext="24"  index="5" type="text" content="英雄橙色品质解锁" colorr="255" colorg="0.99960001185536" colorb="1.02255006786436" font="FZY3JW--GB1-0" fontsize="16.1395702362061" visible="true" opacity="255" width="200" height="24" posx="-49" posy="8" bounds1="955" bounds2="601" bounds3="1155" bounds4="625" />
		<Layer code="Img_basemap_1" type="image" res="img_DJBB_0012"  index="6" visible="true" opacity="255" width="282" height="46" posx="-246" posy="244" bounds1="717" bounds2="354" bounds3="999" bounds4="400" />
		<Layer code="Text" fonttext="30"  index="7" type="text" content="解锁技能" colorr="255" colorg="227.996520996094" colorb="171.001281738281" font="FZY3JW--GB1-0" fontsize="20.1744594573975" visible="true" opacity="255" width="124" height="30" posx="-246" posy="245" bounds1="796" bounds2="361" bounds3="920" bounds4="391" />
	</Layer>
	<Layer code="Img_light" type="image" res="img_BZ_0002"  index="6" visible="true" opacity="255" width="794" height="106" posx="-8" posy="359" bounds1="699" bounds2="209" bounds3="1493" bounds4="315" />
	<Layer code="Text_lgoods" fonttext="47"  index="7" type="text" content="升品预览" colorr="255" colorg="233.000335693359" colorb="187.001037597656" font="FZY3JW--GB1-0" fontsize="17.8465824127197" visible="true" opacity="255" width="193" height="45" posx="-7.5" posy="360.5" bounds1="1000" bounds2="238" bounds3="1193" bounds4="283" />
</UIScene>

